sklearn/__init__.py
sklearn/_config.py
sklearn/_distributor_init.py
sklearn/_isotonic.cpython-310-arm-linux-gnueabihf.so
sklearn/_min_dependencies.py
sklearn/base.py
sklearn/calibration.py
sklearn/conftest.py
sklearn/discriminant_analysis.py
sklearn/dummy.py
sklearn/exceptions.py
sklearn/isotonic.py
sklearn/kernel_approximation.py
sklearn/kernel_ridge.py
sklearn/multiclass.py
sklearn/multioutput.py
sklearn/naive_bayes.py
sklearn/pipeline.py
sklearn/random_projection.py
sklearn/setup.py
sklearn/__check_build/__init__.py
sklearn/__check_build/_check_build.cpython-310-arm-linux-gnueabihf.so
sklearn/__check_build/setup.py
sklearn/_build_utils/__init__.py
sklearn/_build_utils/openmp_helpers.py
sklearn/_build_utils/pre_build_helpers.py
sklearn/_loss/__init__.py
sklearn/_loss/glm_distribution.py
sklearn/_loss/tests/__init__.py
sklearn/_loss/tests/test_glm_distribution.py
sklearn/cluster/__init__.py
sklearn/cluster/_affinity_propagation.py
sklearn/cluster/_agglomerative.py
sklearn/cluster/_bicluster.py
sklearn/cluster/_birch.py
sklearn/cluster/_dbscan.py
sklearn/cluster/_dbscan_inner.cpython-310-arm-linux-gnueabihf.so
sklearn/cluster/_feature_agglomeration.py
sklearn/cluster/_hierarchical_fast.cpython-310-arm-linux-gnueabihf.so
sklearn/cluster/_k_means_elkan.cpython-310-arm-linux-gnueabihf.so
sklearn/cluster/_k_means_fast.cpython-310-arm-linux-gnueabihf.so
sklearn/cluster/_k_means_fast.pxd
sklearn/cluster/_k_means_lloyd.cpython-310-arm-linux-gnueabihf.so
sklearn/cluster/_kmeans.py
sklearn/cluster/_mean_shift.py
sklearn/cluster/_optics.py
sklearn/cluster/_spectral.py
sklearn/cluster/setup.py
sklearn/cluster/tests/__init__.py
sklearn/cluster/tests/common.py
sklearn/cluster/tests/test_affinity_propagation.py
sklearn/cluster/tests/test_bicluster.py
sklearn/cluster/tests/test_birch.py
sklearn/cluster/tests/test_dbscan.py
sklearn/cluster/tests/test_feature_agglomeration.py
sklearn/cluster/tests/test_hierarchical.py
sklearn/cluster/tests/test_k_means.py
rnl_scikit_learn-1.1.dev0.dist-info/COPYING
rnl_scikit_learn-1.1.dev0.dist-info/METADATA
rnl_scikit_learn-1.1.dev0.dist-info/WHEEL
rnl_scikit_learn-1.1.dev0.dist-info/top_level.txt
rnl_scikit_learn-1.1.dev0.dist-info/RECORD
